Metadata-Version: 1.2
Name: py-game-of-life
Version: 1.0.3
Summary: Conway's Game of Life Simulation, implemented with pygame
Home-page: https://github.com/BodaSadalla98/Cookbook/tree/main/python/game_of_live
Author: BodaSadalla
Author-email: boda998@yahoo.com
License: GPL-3.0
Platform: UNKNOWN
Requires-Python: >=3.0
